zxcv/TicTacToe.py
zxcv/call.py
zxcv/source.py
zxcv-2.0.dist-info/LICENSE.txt
zxcv-2.0.dist-info/METADATA
zxcv-2.0.dist-info/WHEEL
zxcv-2.0.dist-info/entry_points.txt
zxcv-2.0.dist-info/top_level.txt
zxcv-2.0.dist-info/RECORD
