Metadata-Version: 2.1
Name: zxcv
Version: 2.0
Summary: A Python package to play tic tac toe
Home-page: https://github.com/tirth-2001/ttt.git
Author: Tirth Patel
Author-email: tirthgpatel.27@gmail.com
License: MIT
Platform: UNKNOWN
Classifier: License :: OSI Approved :: MIT License
Classifier: Programming Language :: Python :: 3
Classifier: Programming Language :: Python :: 3.7
